neogr_model/__init__.py
neogr_model/client.py
neogr_model/model.py
neogr_model-0.0.2.dist-info/METADATA
neogr_model-0.0.2.dist-info/WHEEL
neogr_model-0.0.2.dist-info/RECORD
